falcon_sentry/__init__.py
falcon_sentry/sentry.py
falcon_sentry-0.2.2.dist-info/LICENSE
falcon_sentry-0.2.2.dist-info/METADATA
falcon_sentry-0.2.2.dist-info/WHEEL
falcon_sentry-0.2.2.dist-info/top_level.txt
falcon_sentry-0.2.2.dist-info/RECORD
