Metadata-Version: 2.1
Name: falcon-sentry
Version: 0.2.2
Summary: TODO
Home-page: https://code.richard.do/richardARPANET/falcon-sentry/
Author: Richard O'Dwyer
Author-email: richard@richard.do
License: Apache 2.0
Platform: UNKNOWN
Classifier: Intended Audience :: Developers
Classifier: Operating System :: OS Independent
Classifier: Programming Language :: Python
Classifier: Programming Language :: Python :: 3.6
Classifier: Topic :: Internet :: WWW/HTTP
Requires-Dist: falcon
Requires-Dist: sentry-sdk
Requires-Dist: wheel
